codegyan/__init__.py
codegyan/client.py
codegyan/compiler.py
codegyan/tools.py
codegyan-1.0.0.dist-info/LICENSE.md
codegyan-1.0.0.dist-info/METADATA
codegyan-1.0.0.dist-info/WHEEL
codegyan-1.0.0.dist-info/top_level.txt
codegyan-1.0.0.dist-info/RECORD
