Metadata-Version: 2.1
Name: codegyan
Version: 1.0.0
Summary: A Python library to interact with the Codegyan API
Home-page: https://github.com/Codegyan-LLC/codegyan-python
Author: Prathmesh Yelne
Author-email: prathmeshyelne@codegyan.in
Keywords: codegyan,api,codex,client,sdk,prathmeshyelne
Classifier: Programming Language :: Python :: 3
Classifier: License :: OSI Approved :: MIT License
Classifier: Operating System :: OS Independent
Requires-Python: >=3.6
License-File: LICENSE.md
Requires-Dist: requests
